<?xml version='1.0' encoding='utf-8'?>
<TextureAtlas imagePath="Menu_Pico.png"><SubTexture name="M Pico Idle0000" x="1230" y="434" width="403" height="427" frameX="0" frameY="-6" frameWidth="420" frameHeight="435" />
<SubTexture name="M Pico Idle0001" x="1230" y="434" width="403" height="427" frameX="0" frameY="-6" frameWidth="420" frameHeight="435" />
<SubTexture name="M Pico Idle0002" x="0" y="435" width="409" height="434" frameX="0" frameY="0" frameWidth="420" frameHeight="435" />
<SubTexture name="M Pico Idle0003" x="0" y="435" width="409" height="434" frameX="0" frameY="0" frameWidth="420" frameHeight="435" />
<SubTexture name="M Pico Idle0004" x="409" y="435" width="415" height="434" frameX="-4" frameY="0" frameWidth="420" frameHeight="435" />
<SubTexture name="M Pico Idle0005" x="1230" y="0" width="411" height="434" frameX="-8" frameY="0" frameWidth="420" frameHeight="435" />
<SubTexture name="M Pico Idle0006" x="0" y="0" width="411" height="435" frameX="-8" frameY="0" frameWidth="420" frameHeight="435" />
<SubTexture name="M Pico Idle0007" x="411" y="0" width="409" height="435" frameX="-10" frameY="0" frameWidth="420" frameHeight="435" />
<SubTexture name="M Pico Idle0008" x="820" y="0" width="410" height="435" frameX="-10" frameY="0" frameWidth="420" frameHeight="435" />
<SubTexture name="M Pico Idle0009" x="820" y="0" width="410" height="435" frameX="-10" frameY="0" frameWidth="420" frameHeight="435" />
<SubTexture name="M Pico Idle0010" x="820" y="0" width="410" height="435" frameX="-10" frameY="0" frameWidth="420" frameHeight="435" />
<SubTexture name="M Pico Idle0011" x="820" y="0" width="410" height="435" frameX="-10" frameY="0" frameWidth="420" frameHeight="435" />
<SubTexture name="M Pico Idle0012" x="820" y="0" width="410" height="435" frameX="-10" frameY="0" frameWidth="420" frameHeight="435" />
<SubTexture name="M Pico Idle0013" x="820" y="0" width="410" height="435" frameX="-10" frameY="0" frameWidth="420" frameHeight="435" />
</TextureAtlas>
